<?xml version="1.0" encoding="UTF-8"?>
<?xml-stylesheet href="../sensors/xslt/speciment2html.xsl" type="text/xsl"?>
<cs:resources xmlns:cs="https://igsn.csiro.au/schemas/3.0" xmlns:xsi="http://www.w3.org/2001/XMLSchema-instance" xmlns:xlink="http://www.w3.org/1999/xlink/namespace" xsi:schemaLocation="https://igsn.csiro.au/schemas/3.0 https://igsn.csiro.au/schemas/3.0/igsn-csiro-v3.0.xsd">
  <cs:resource registeredObjectType="http://pid.geoscience.gov.au/def/voc/igsn-codelists/PhysicalSample">
    <cs:resourceIdentifier>uuid-8ee1e9f4-ca8c-11ee-8c69-daf69f6cfb8a</cs:resourceIdentifier>
    <cs:landingPage>http://www.get-it.it/objects/samples/specimen_8ee1e9f4-ca8c-11ee-8c69-daf69f6cfb8a.xml</cs:landingPage>
    <cs:isPublic>true</cs:isPublic>
    <cs:resourceTitle>Sample LM98_13A</cs:resourceTitle>
    <cs:resourceTypes>
      <cs:resourceType>http://vocabulary.odm2.org/specimentype/thinSection</cs:resourceType>
    </cs:resourceTypes>
    <cs:materialTypes>
      <cs:materialType>http://vocabulary.odm2.org/medium/sediment</cs:materialType>
    </cs:materialTypes>
    <cs:purpose>Measurements of pigments in the Lakes by CNR-ISE</cs:purpose>
    <cs:sampledFeatures>
      <cs:sampledFeature sampledFeatureURI="https://deims.org/f30007c4-8a6e-4f11-ab87-569db54638fe"/>
    </cs:sampledFeatures>
    <cs:location>
      <cs:locality localityURI="https://deims.org/locations/4930521a-596f-4e6f-90b8-29696b8c1c98"/>
      <cs:geometry srid="https://epsg.io/8311" verticalDatum="https://epsg.io/4326">POLYGON ((8.61638 45.96204, 8.642529 45.96204, 8.642529 45.94946, 8.61638 45.94946, 8.61638 45.96204))</cs:geometry>
    </cs:location>
    <cs:date>
      <cs:timeInstant>2008-02-12</cs:timeInstant>
    </cs:date>
    <cs:method methodURI="https://doi.org/10.1007/BF02544119"/>
    <cs:campaign>https://deims.org/activity/50d7a52d-e384-4ed4-9976-5bf9c8302843</cs:campaign>
    <cs:curationDetails>
      <cs:curation>
        <cs:curator>Kov치cs J치nos</cs:curator>
        <cs:curatingInstitution institutionURI="https://ror.org/02db0k"/>
      </cs:curation>
      <cs:curation>
        <cs:curator>Jane Doe</cs:curator>
        <cs:curatingInstitution institutionURI="https://ror.org/02db0k"/>
      </cs:curation>
      <cs:curation>
        <cs:curator>Mario Rossi</cs:curator>
        <cs:curatingInstitution institutionURI="https://ror.org/02wxw"/>
      </cs:curation>
    </cs:curationDetails>
    <cs:contributors>
      <cs:contributor contributorType="http://inspire.ec.europa.eu/metadata-codelist/ResponsiblePartyRole/owner">
        <cs:contributorName>Kov치cs J치nos</cs:contributorName>
        <cs:contributorIdentifier contributorIdentifierType="http://pid.geoscience.gov.au/def/voc/igsn-codelists/ORCID">https://orcid.org/0000-0003-3627</cs:contributorIdentifier>
      </cs:contributor>
      <cs:contributor contributorType="http://inspire.ec.europa.eu/metadata-codelist/ResponsiblePartyRole/custodian">
        <cs:contributorName>Jane Doe</cs:contributorName>
        <cs:contributorIdentifier contributorIdentifierType="http://pid.geoscience.gov.au/def/voc/igsn-codelists/ORCID">https://orcid.org/0000-0003-3515</cs:contributorIdentifier>
      </cs:contributor>
      <cs:contributor contributorType="http://inspire.ec.europa.eu/metadata-codelist/ResponsiblePartyRole/owner">
        <cs:contributorName>Mario Rossi</cs:contributorName>
        <cs:contributorIdentifier contributorIdentifierType="http://pid.geoscience.gov.au/def/voc/igsn-codelists/ORCID">https://orcid.org/0000-0002-7997</cs:contributorIdentifier>
      </cs:contributor>
    </cs:contributors>
    <cs:relatedResources>
      <cs:relatedResource relatedResourceIdentifierType="http://pid.geoscience.gov.au/def/voc/igsn-codelists/DOI" relationType="http://pid.geoscience.gov.au/def/voc/igsn-codelists/IsDerivedFrom">10.xxxx/hahaahoadho</cs:relatedResource>
      <cs:relatedResource relatedResourceIdentifierType="http://pid.geoscience.gov.au/def/voc/igsn-codelists/DOI" relationType="http://pid.geoscience.gov.au/def/voc/igsn-codelists/IsDerivedFrom">10.xxxx/hahaahoadhb</cs:relatedResource>
    </cs:relatedResources>
    <cs:comments>Description of the sample</cs:comments>
    <cs:logDate eventType="registered">2024-02-13</cs:logDate>
  </cs:resource>
</cs:resources>
